agldata/__init__.py
agldata/_version.py
agldata/argvalidation.py
agldata/setup.py
agldata/stringdata.py
agldata/datafiles/__init__.py
agldata/datafiles/abe_and_watanabe_2011_natneurosci.yaml
agldata/datafiles/attaheri_etal_2015_brainlanguage.yaml
agldata/datafiles/chenetal_2015_animcogn.yaml
agldata/datafiles/chentencate_2015_behproc.yaml
agldata/datafiles/endressetal_2010_animcogn.yaml
agldata/datafiles/knowltonsquire_1996_jexppsy.yaml
agldata/datafiles/mockexample.yaml
agldata/datafiles/saffranetal_2008_cog.yaml
agldata/datafiles/saffranetal_2008_cog_exp5.yaml
agldata/datafiles/vanheijningenetal_2013_animcogn.yaml
agldata/datafiles/wilsonetal_2013_jneurosci.yaml
agldata/datafiles/wilsonetal_2015_ejn.yaml
agldata/datafiles/wilsonetal_2015_natcomm.yaml
agldata/tests/__init__.py
agldata/tests/test_datafiles.py
agldata/tests/test_stringdata.py
agldata-0.1.0.dist-info/LICENSE
agldata-0.1.0.dist-info/METADATA
agldata-0.1.0.dist-info/WHEEL
agldata-0.1.0.dist-info/top_level.txt
agldata-0.1.0.dist-info/RECORD
